bedrock_genai_util/AnthropicBedrockUtil.py
bedrock_genai_util/AwsTitanBedrockUtil.py
bedrock_genai_util/BedrockUtil.py
bedrock_genai_util/CohereBedrockUtil.py
bedrock_genai_util/MetaBedrockUtil.py
bedrock_genai_util/MistralBedrockUtil.py
bedrock_genai_util/TextCompletionUtil.py
bedrock_genai_util/__init__.py
bedrock_genai_util/agent_service.py
bedrock_genai_util/model_map.py
bedrock_genai_util/prompt_service.py
bedrock_genai_util-0.0.3.dist-info/LICENSE.txt
bedrock_genai_util-0.0.3.dist-info/METADATA
bedrock_genai_util-0.0.3.dist-info/WHEEL
bedrock_genai_util-0.0.3.dist-info/top_level.txt
bedrock_genai_util-0.0.3.dist-info/RECORD
