Metadata-Version: 2.1
Name: bedrock_genai_util
Version: 0.0.3
Summary: Library for Bedrock based GenAI Utility for AWS Based development
Author-email: Biprajeet Kar <biprokvs@gmail.com>
Maintainer-email: Biprajeet Kar <biprokvs@gmail.com>
License: MIT License
Classifier: Programming Language :: Python :: 3
Classifier: License :: OSI Approved :: MIT License
Classifier: Operating System :: OS Independent
Requires-Python: >=3.8
License-File: LICENSE.txt
Requires-Dist: click
